CHANGES.rst
MANIFEST.in
README.rst
setup.py
cryptoassets/__init__.py
cryptoassets.core.egg-info/PKG-INFO
cryptoassets.core.egg-info/SOURCES.txt
cryptoassets.core.egg-info/dependency_links.txt
cryptoassets.core.egg-info/entry_points.txt
cryptoassets.core.egg-info/not-zip-safe
cryptoassets.core.egg-info/requires.txt
cryptoassets.core.egg-info/top_level.txt
cryptoassets/core/__init__.py
cryptoassets/core/app.py
cryptoassets/core/configure.py
cryptoassets/core/models.py
cryptoassets/core/backend/base.py
cryptoassets/core/backend/bitcoind.py
cryptoassets/core/backend/blockchain.py
cryptoassets/core/backend/blockio.py
cryptoassets/core/backend/httpwalletnotify.py
cryptoassets/core/backend/null.py
cryptoassets/core/backend/pipewalletnotify.py
cryptoassets/core/backend/rediswalletnotify.py
cryptoassets/core/backend/sochainwalletnotify.py
cryptoassets/core/backend/transactionupdater.py
cryptoassets/core/coin/defaults.py
cryptoassets/core/coin/registry.py
cryptoassets/core/coin/validate.py
cryptoassets/core/coin/applebyte/__init__.py
cryptoassets/core/coin/applebyte/models.py
cryptoassets/core/coin/bitcoin/__init__.py
cryptoassets/core/coin/bitcoin/models.py
cryptoassets/core/coin/dogecoin/models.py
cryptoassets/core/coin/litecoin/models.py
cryptoassets/core/event/base.py
cryptoassets/core/event/events.py
cryptoassets/core/event/http.py
cryptoassets/core/event/python.py
cryptoassets/core/event/registry.py
cryptoassets/core/event/script.py
cryptoassets/core/service/defaultlogging.py
cryptoassets/core/service/main.py
cryptoassets/core/service/status.py
cryptoassets/core/tests/__init__.py
cryptoassets/core/tests/base.py
cryptoassets/core/tests/bitcoind.config.yaml
cryptoassets/core/tests/bitcoind.droneio.config.yaml
cryptoassets/core/tests/blockio-bitcoin.config.yaml
cryptoassets/core/tests/blockio-dogecoin.config.yaml
cryptoassets/core/tests/broken-config-no-backend.yaml
cryptoassets/core/tests/null.config.yaml
cryptoassets/core/tests/sample-config.yaml
cryptoassets/core/tests/service.config.yaml
cryptoassets/core/tests/sqlite.conflictresolver.config.yaml
cryptoassets/core/tests/startstop.config.yaml
cryptoassets/core/tests/test_bitcoind.py
cryptoassets/core/tests/test_block_io.py
cryptoassets/core/tests/test_blockchain.py
cryptoassets/core/tests/test_coin.py
