Metadata-Version: 1.1
Name: cryptoassets.core
Version: 0.0
Summary: A Python framework for building Bitcoin, other cryptocurrency (altcoin) and cryptoassets services
Home-page: https://bitbucket.org/miohtama/cryptoassets
Author: Mikko Ohtamaa
Author-email: mikko@opensourcehacker.com
License: UNKNOWN
Keywords: bitcoin litecoin dogecoin sqlalchemy
Platform: UNKNOWN
Classifier: Development Status :: 4 - Beta
Classifier: Programming Language :: Python
Classifier: Intended Audience :: Developers
Classifier: Programming Language :: Python :: 3.4
Classifier: Programming Language :: Python :: 3
Classifier: License :: OSI Approved :: MIT License
Classifier: Topic :: Security :: Cryptography
Classifier: Intended Audience :: Financial and Insurance Industry
